{
  "type": "FeatureCollection",
  "name": "GBIF_US_publishers_2023-02-21",
  "features": [
    {
      "type": "Feature",
      "properties": {
        "popupContent": "<a href="https://www.gbif.org/publisher/ae447c50-b8a8-11d8-92a4-b8a03c50a862">Florida Gulf Coast University</a><br/>Ft Myers<br/>Florida<br/>US<br/>33965"
        },
      "geometry": {
        "type": "Point",
        "coordinates": [
          -81.7734,
          26.46364
        ]
      }
    },
	{
      "type": "Feature",
      "properties": {
        "popupContent": "Steve's Home"
        },
      "geometry": {
        "type": "Point",
        "coordinates": [
          -90,
          30
        ]
      }
    },
    {
      "type": "Feature",
      "properties": {
        "popupContent": {
          "name": "Reptiles and Amphibians",
          "city": "Lawrence",
          "province": "Kansas",
          "country": "US",
          "postalCode": "66045"
        }
      },
      "geometry": {
        "type": "Point",
        "coordinates": [
          -95.24355,
          38.95945
        ]
      }
    }
  ]
}